.gitignore
MANIFEST.in
README.rst
setup.py
cython_ipp/__init__.py
cython_ipp/ipp.pxd
cython_ipp.egg-info/PKG-INFO
cython_ipp.egg-info/SOURCES.txt
cython_ipp.egg-info/dependency_links.txt
cython_ipp.egg-info/not-zip-safe
cython_ipp.egg-info/top_level.txt